regressalot/__init__.py
regressalot/core.py
regressalot/models.py
regressalot-0.1.0.dist-info/licenses/LICENSE
regressalot-0.1.0.dist-info/METADATA
regressalot-0.1.0.dist-info/WHEEL
regressalot-0.1.0.dist-info/top_level.txt
regressalot-0.1.0.dist-info/RECORD
